[
    {
        "Nom": "MARIN",
        "Prénom": "Sarah",
        "Mail": "",
        "Etat": "",
        "Commence": "",
        "terminé": "",
        "tempas passe": "",
        "Note/10": "7.83"
    },
    {
        "Nom": "LEFORT",
        "Prénom": "Louis",
        "Mail": "",
        "Etat": "",
        "Commence": "",
        "terminé": "",
        "tempas passe": "",
        "Note/10": "4.26"
    },
    {
        "Nom": "ROUSSEAU",
        "Prénom": "Eva",
        "Mail": "",
        "Etat": "",
        "Commence": "",
        "terminé": "",
        "tempas passe": "",
        "Note/10": "8.97"
    },
    {
        "Nom": "DEBRAY",
        "Prénom": "Théo",
        "Mail": "",
        "Etat": "",
        "Commence": "",
        "terminé": "",
        "tempas passe": "",
        "Note/10": "2.51"
    },
    {
        "Nom": "HENIN",
        "Prénom": "Clara",
        "Mail": "",
        "Etat": "",
        "Commence": "",
        "terminé": "",
        "tempas passe": "",
        "Note/10": "9.74"
    },
    {
        "Nom": "HERVÉ",
        "Prénom": "Adam",
        "Mail": "",
        "Etat": "",
        "Commence": "",
        "terminé": "",
        "tempas passe": "",
        "Note/10": "5.62"
    },
    {
        "Nom": "GOSSELIN",
        "Prénom": "Juliette",
        "Mail": "",
        "Etat": "",
        "Commence": "",
        "terminé": "",
        "tempas passe": "",
        "Note/10": "6.38"
    },
    {
        "Nom": "AUVRAY",
        "Prénom": "Tom",
        "Mail": "",
        "Etat": "",
        "Commence": "",
        "terminé": "",
        "tempas passe": "",
        "Note/10": "3.91"
    },
    {
        "Nom": "PIERRE",
        "Prénom": "Rose",
        "Mail": "",
        "Etat": "",
        "Commence": "",
        "terminé": "",
        "tempas passe": "",
        "Note/10": "8.15"
    },
    {
        "Nom": "MALLET",
        "Prénom": "Jules",
        "Mail": "",
        "Etat": "",
        "Commence": "",
        "terminé": "",
        "tempas passe": "",
        "Note/10": "6.99"
    },
    {
        "Nom": "THIERRY",
        "Prénom": "Lina",
        "Mail": "",
        "Etat": "",
        "Commence": "",
        "terminé": "",
        "tempas passe": "",
        "Note/10": "4.73"
    },
    {
        "Nom": "NAUDIN",
        "Prénom": "Maël",
        "Mail": "",
        "Etat": "",
        "Commence": "",
        "terminé": "",
        "tempas passe": "",
        "Note/10": "7.41"
    },
    {
        "Nom": "BONNIN",
        "Prénom": "Anna",
        "Mail": "",
        "Etat": "",
        "Commence": "",
        "terminé": "",
        "tempas passe": "",
        "Note/10": "5.09"
    },
    {
        "Nom": "BERTRAND",
        "Prénom": "Enzo",
        "Mail": "",
        "Etat": "",
        "Commence": "",
        "terminé": "",
        "tempas passe": "",
        "Note/10": "8.62"
    },
    {
        "Nom": "GAUTHIER",
        "Prénom": "Elsa",
        "Mail": "",
        "Etat": "",
        "Commence": "",
        "terminé": "",
        "tempas passe": "",
        "Note/10": "3.17"
    },
    {
        "Nom": "ROLLAND",
        "Prénom": "Raphaël",
        "Mail": "",
        "Etat": "",
        "Commence": "",
        "terminé": "",
        "tempas passe": "",
        "Note/10": "9.28"
    },
    {
        "Nom": "POIRIER",
        "Prénom": "Manon",
        "Mail": "",
        "Etat": "",
        "Commence": "",
        "terminé": "",
        "tempas passe": "",
        "Note/10": "7.06"
    },
    {
        "Nom": "RENAULT",
        "Prénom": "Nathan",
        "Mail": "",
        "Etat": "",
        "Commence": "",
        "terminé": "",
        "tempas passe": "",
        "Note/10": "2.84"
    },
    {
        "Nom": "PROUST",
        "Prénom": "Emma",
        "Mail": "",
        "Etat": "",
        "Commence": "",
        "terminé": "",
        "tempas passe": "",
        "Note/10": "6.76"
    },
    {
        "Nom": "BARBIER",
        "Prénom": "Hugo",
        "Mail": "",
        "Etat": "",
        "Commence": "",
        "terminé": "",
        "tempas passe": "",
        "Note/10": "8.49"
    },
    {
        "Nom": "TESSIER",
        "Prénom": "Inès",
        "Mail": "",
        "Etat": "",
        "Commence": "",
        "terminé": "",
        "tempas passe": "",
        "Note/10": "4.57"
    },
    {
        "Nom": "HEBERT",
        "Prénom": "Ethan",
        "Mail": "",
        "Etat": "",
        "Commence": "",
        "terminé": "",
        "tempas passe": "",
        "Note/10": "9.09"
    },
    {
        "Nom": "RENARD",
        "Prénom": "Chloé",
        "Mail": "",
        "Etat": "",
        "Commence": "",
        "terminé": "",
        "tempas passe": "",
        "Note/10": "3.62"
    },
    {
        "Nom": "DUPONT",
        "Prénom": "Noah",
        "Mail": "",
        "Etat": "",
        "Commence": "",
        "terminé": "",
        "tempas passe": "",
        "Note/10": "5.83"
    },
    {
        "Nom": "MATHIEU",
        "Prénom": "Léa",
        "Mail": "",
        "Etat": "",
        "Commence": "",
        "terminé": "",
        "tempas passe": "",
        "Note/10": "7.19"
    },
    {
        "Nom": "CARPENTIER",
        "Prénom": "Liam",
        "Mail": "",
        "Etat": "",
        "Commence": "",
        "terminé": "",
        "tempas passe": "",
        "Note/10": "4.93"
    },
    {
        "Nom": "LEGROS",
        "Prénom": "Zoé",
        "Mail": "",
        "Etat": "",
        "Commence": "",
        "terminé": "",
        "tempas passe": "",
        "Note/10": "8.38"
    },
    {
        "Nom": "NOEL",
        "Prénom": "Arthur",
        "Mail": "",
        "Etat": "",
        "Commence": "",
        "terminé": "",
        "tempas passe": "",
        "Note/10": "2.39"
    },
    {
        "Nom": "ROBIN",
        "Prénom": "Jade",
        "Mail": "",
        "Etat": "",
        "Commence": "",
        "terminé": "",
        "tempas passe": "",
        "Note/10": "6.14"
    },
    {
        "Nom": "GARNIER",
        "Prénom": "Lucas",
        "Mail": "",
        "Etat": "",
        "Commence": "",
        "terminé": "",
        "tempas passe": "",
        "Note/10": "9.52"
    },
    {
        "Nom": "MOREAU",
        "Prénom": "Camille",
        "Mail": "",
        "Etat": "",
        "Commence": "",
        "terminé": "",
        "tempas passe": "",
        "Note/10": "5.47"
    },
    {
        "Nom": "MASSON",
        "Prénom": "Gabriel",
        "Mail": "",
        "Etat": "",
        "Commence": "",
        "terminé": "",
        "tempas passe": "",
        "Note/10": "7.73"
    },
    {
        "Nom": "MOREL",
        "Prénom": "Louise",
        "Mail": "",
        "Etat": "",
        "Commence": "",
        "terminé": "",
        "tempas passe": "",
        "Note/10": "3.48"
    },
    {
        "Nom": "LEFEBVRE",
        "Prénom": "Léo",
        "Mail": "",
        "Etat": "",
        "Commence": "",
        "terminé": "",
        "tempas passe": "",
        "Note/10": "8.86"
    },
    {
        "Nom": "LAURENT",
        "Prénom": "Sarah",
        "Mail": "",
        "Etat": "",
        "Commence": "",
        "terminé": "",
        "tempas passe": "",
        "Note/10": "6.22"
    },
    {
        "Nom": "MOREL",
        "Prénom": "Louis",
        "Mail": "",
        "Etat": "",
        "Commence": "",
        "terminé": "",
        "tempas passe": "",
        "Note/10": "4.05"
    },
    {
        "Nom": "PERRIN",
        "Prénom": "Eva",
        "Mail": "",
        "Etat": "",
        "Commence": "",
        "terminé": "",
        "tempas passe": "",
        "Note/10": "7.58"
    },
    {
        "Nom": "PERROT",
        "Prénom": "Théo",
        "Mail": "",
        "Etat": "",
        "Commence": "",
        "terminé": "",
        "tempas passe": "",
        "Note/10": "2.97"
    },
    {
        "Nom": "REMY",
        "Prénom": "Clara",
        "Mail": "",
        "Etat": "",
        "Commence": "",
        "terminé": "",
        "tempas passe": "",
        "Note/10": "9.19"
    }
]